relic/ucs/__init__.py
relic/ucs/py.typed
relic_tool_ucs-1.1.0.dist-info/LICENSE.txt
relic_tool_ucs-1.1.0.dist-info/METADATA
relic_tool_ucs-1.1.0.dist-info/WHEEL
relic_tool_ucs-1.1.0.dist-info/top_level.txt
relic_tool_ucs-1.1.0.dist-info/RECORD
