Metadata-Version: 2.2
Name: relic-tool-ucs
Version: 1.1.0
Summary: A library for reading / writing Relic's UCS (Language) files.
Author: Marcus Kertesz
Project-URL: Bug Tracker, https://github.com/MAK-Relic-Tool/Issue-Tracker/issues
Project-URL: Homepage, https://github.com/MAK-Relic-Tool/Relic-Tool-UCS
Classifier: Programming Language :: Python :: 3 :: Only
Classifier: Programming Language :: Python :: 3.9
Classifier: Programming Language :: Python :: 3.10
Classifier: Programming Language :: Python :: 3.11
Classifier: Programming Language :: Python :: 3.12
Classifier: Programming Language :: Python :: 3.13
Classifier: License :: OSI Approved :: GNU General Public License v3 (GPLv3)
Classifier: Operating System :: OS Independent
Requires-Python: >=3.9
License-File: LICENSE.txt
Requires-Dist: relic-tool-core>=2.0.0
